LICENSE
README.md
setup.py
HiveNetGRPC.egg-info/PKG-INFO
HiveNetGRPC.egg-info/SOURCES.txt
HiveNetGRPC.egg-info/dependency_links.txt
HiveNetGRPC.egg-info/entry_points.txt
HiveNetGRPC.egg-info/not-zip-safe
HiveNetGRPC.egg-info/requires.txt
HiveNetGRPC.egg-info/top_level.txt
HiveNetGRpc/__init__.py
HiveNetGRpc/client.py
HiveNetGRpc/enum.py
HiveNetGRpc/msg_formater.py
HiveNetGRpc/server.py
HiveNetGRpc/tool.py
HiveNetGRpc/proto/__init__.py
HiveNetGRpc/proto/msg_bytes.proto
HiveNetGRpc/proto/msg_bytes_pb2.py
HiveNetGRpc/proto/msg_bytes_pb2_grpc.py
HiveNetGRpc/proto/msg_json.proto
HiveNetGRpc/proto/msg_json_pb2.py
HiveNetGRpc/proto/msg_json_pb2_grpc.py
HiveNetGRpc/proto/proto_generate.py